sourceinspect/__init__.py
sourceinspect/autodetect.py
sourceinspect/blender.py
sourceinspect/code.py
sourceinspect/dill.py
sourceinspect/ipython.py
sourceinspect/remote.py
sourceinspect/std.py
sourceinspect-0.0.3.dist-info/METADATA
sourceinspect-0.0.3.dist-info/WHEEL
sourceinspect-0.0.3.dist-info/top_level.txt
sourceinspect-0.0.3.dist-info/RECORD
